crabigator/__init__.py
crabigator/wanikani.py
crabigator/tests/__init__.py
crabigator/tests/test_wanikani.py
crabigator-0.1.5.dist-info/top_level.txt
crabigator-0.1.5.dist-info/METADATA
crabigator-0.1.5.dist-info/DESCRIPTION.rst
crabigator-0.1.5.dist-info/metadata.json
crabigator-0.1.5.dist-info/WHEEL
crabigator-0.1.5.dist-info/RECORD
