Metadata-Version: 2.0
Name: crabigator
Version: 0.1.5
Summary: Python Library for WaniKani
Home-page: http://github.com/jonesinator/crabigator/
Author: Aaron Jones
Author-email: aaron@jonesinator.com
License: MIT
Platform: UNKNOWN
Classifier: Development Status :: 3 - Alpha
Classifier: Intended Audience :: Developers
Classifier: License :: OSI Approved :: MIT License
Classifier: Natural Language :: English
Classifier: Operating System :: OS Independent
Classifier: Programming Language :: Python :: 2.7
Classifier: Programming Language :: Python :: 3.4
